README.rst
setup.py
zinnia2puput/__init__.py
zinnia2puput/management/__init__.py
zinnia2puput/management/commands/__init__.py
zinnia2puput/management/commands/zinnia2puput.py
zinnia_to_puput.egg-info/PKG-INFO
zinnia_to_puput.egg-info/SOURCES.txt
zinnia_to_puput.egg-info/dependency_links.txt
zinnia_to_puput.egg-info/requires.txt
zinnia_to_puput.egg-info/top_level.txt